{"expireTime":9007200896590193000,"key":"90d045aa3dea6479d0b64bf1071b8eff","val":{"name":"IMAGE_PROCESSING","inputPaths":["/Users/koushikaravalli/work-stuff/koushik-aravalli.github.io/content/assets/profile-pic.png"],"outputDir":"/Users/koushikaravalli/work-stuff/koushik-aravalli.github.io/public/static/91ec29bd7987216c267be5bd42dda55c","args":{"isLazy":false,"operations":[{"outputPath":"8ba1e/profile-pic.png","args":{"height":50,"width":50,"cropFocus":17,"toFormat":"png","fit":"cover","background":"rgba(0,0,0,1)"}},{"outputPath":"f937a/profile-pic.png","args":{"height":75,"width":75,"cropFocus":17,"toFormat":"png","fit":"cover","background":"rgba(0,0,0,1)"}}],"pluginOptions":{"base64Width":20,"forceBase64Format":"","useMozJpeg":false,"stripMetadata":true,"lazyImageGeneration":true,"defaultQuality":50,"failOnError":true,"plugins":[]}}}}